MANIFEST.in
README.rst
setup.py
jarg/__init__.py
jarg/__main__.py
jarg/cli.py
jarg/dialects.py
jarg/jsonform.py
jarg.egg-info/PKG-INFO
jarg.egg-info/SOURCES.txt
jarg.egg-info/dependency_links.txt
jarg.egg-info/entry_points.txt
jarg.egg-info/not-zip-safe
jarg.egg-info/requires.txt
jarg.egg-info/top_level.txt