Metadata-Version: 1.1
Name: jarg
Version: 0.4.0
Summary: A shorthand data serialization/encoding tool
Home-page: http://github.com/jdp/jarg
Author: Justin Poliey
Author-email: justin.d.poliey@gmail.com
License: MIT
Platform: UNKNOWN
Classifier: Development Status :: 4 - Beta
Classifier: Environment :: Console
Classifier: Intended Audience :: Developers
Classifier: License :: OSI Approved :: MIT License
Classifier: Natural Language :: English
Classifier: Operating System :: POSIX
Classifier: Programming Language :: Python
Classifier: Programming Language :: Python :: 2
Classifier: Programming Language :: Python :: 3
Classifier: Topic :: Internet
Classifier: Topic :: Utilities
